comp3900_ttt_arena_helpers/__init__.py
comp3900_ttt_arena_helpers/classes.py
comp3900_ttt_arena_helpers/classes.pyi
comp3900_ttt_arena_helpers/py.typed
comp3900_ttt_arena_helpers-0.0.4.dist-info/METADATA
comp3900_ttt_arena_helpers-0.0.4.dist-info/WHEEL
comp3900_ttt_arena_helpers-0.0.4.dist-info/RECORD
