Metadata-Version: 2.1
Name: comp3900_ttt_arena_helpers
Version: 0.0.4
Summary: Helper classes for ttt arena users
Author-email: Kevin Zhong <z5207993@unsw.edu.au>
Requires-Python: >=3.10
